README.rst
setup.py
sparqlkernel/__init__.py
sparqlkernel/__main__.py
sparqlkernel/connection.py
sparqlkernel/constants.py
sparqlkernel/drawgraph.py
sparqlkernel/install.py
sparqlkernel/kernel.py
sparqlkernel/language.py
sparqlkernel/magics.py
sparqlkernel/pygments_sparql.py
sparqlkernel/setlogging.py
sparqlkernel/utils.py
sparqlkernel.egg-info/PKG-INFO
sparqlkernel.egg-info/SOURCES.txt
sparqlkernel.egg-info/dependency_links.txt
sparqlkernel.egg-info/entry_points.txt
sparqlkernel.egg-info/requires.txt
sparqlkernel.egg-info/top_level.txt
sparqlkernel/resources/logo-32x32.png
sparqlkernel/resources/logo-64x64.png
sparqlkernel/resources/sparqlkernel.css